foo_bar_doo
