Metadata-Version: 1.1
Name: foo-bar-doo
Version: 0.2
Summary: foo-bar-doo
Home-page: https://github.com/grindsa/foo-bar-doo
Author: grindsa
Author-email: grindelsack@gmail.com
License: GPL
Platform: any
Classifier: Programming Language :: Python
Classifier: Development Status :: 4 - Beta
Classifier: Natural Language :: German
Classifier: Intended Audience :: Developers
Classifier: License :: OSI Approved :: GNU General Public License v3 or later (GPLv3+)
Classifier: Operating System :: OS Independent
Classifier: Topic :: Software Development :: Libraries :: Python Modules
